{
  "db_name": "PostgreSQL",
  "query": "SELECT * FROM auctions WHERE id = $1",
  "describe": {
    "columns": [
      {
        "ordinal": 0,
        "name": "id",
        "type_info": "Int8"
      },
      {
        "ordinal": 1,
        "name": "battery_id",
        "type_info": "Int4"
      },
      {
        "ordinal": 2,
        "name": "aggregator_id",
        "type_info": "Int4"
      },
      {
        "ordinal": 3,
        "name": "energy_amount",
        "type_info": "Numeric"
      },
      {
        "ordinal": 4,
        "name": "reserve_price",
        "type_info": "Numeric"
      },
      {
        "ordinal": 5,
        "name": "final_price",
        "type_info": "Numeric"
      },
      {
        "ordinal": 6,
        "name": "status",
        "type_info": "Varchar"
      },
      {
        "ordinal": 7,
        "name": "blockchain_tx_hash",
        "type_info": "Varchar"
      },
      {
        "ordinal": 8,
        "name": "started_at",
        "type_info": "Timestamptz"
      },
      {
        "ordinal": 9,
        "name": "settled_at",
        "type_info": "Timestamptz"
      },
      {
        "ordinal": 10,
        "name": "created_at",
        "type_info": "Timestamptz"
      }
    ],
    "parameters": {
      "Left": [
        "Int8"
      ]
    },
    "nullable": [
      false,
      false,
      true,
      false,
      false,
      true,
      false,
      true,
      true,
      true,
      true
    ]
  },
  "hash": "c4249ca78d58332772c34270e905f58376c18919d318d577521a35f318b93366"
}
